{"header":
    ["script", "args", "auto", "tasktype", "hidden", "group", "item", "min", "expect", "max", "unit", "sfc_name"],
 "version": "14.0",
 "sfc_station_id": "DL",
 "devices": {
    "dut": {
        "name": "ftdi",
        "num": 2,
        "sn": ["AQ0011SBA", "AQ000SHLA"]
    }
 },
 "appearance": {
     "columns_hidden": [0, 1, 2, 3, 4, 7, 8, 9, 10, 11],
     "columns_width": [1, 1, 1, 1, 1, 150, 220, 1, 1, 1, 1, 1, 190, 190, 190, 190]
 },
 "behaviors": {
     "barcode-scan": false,
     "firsts": [],
     "actions": [
         {
            "action": "disable_power_check",
            "args": ["win"]
         }
         ,{
            "action": "is_serial_ok",
            "args": ["win", "task"]
         }
         ,{
            "action": "enter_prompt",
            "args": ["win", 0.2, 10]
         }
     ],
     "prepares": [],
     "afters": []
 },
 "test_items":
    [
        {
            "group": "Read ProductID",
            "hidden": false,
            "tasktype": 1,
            "item": "",
            "script": "task_runeach",
            "args": ["read_pid"],
            "auto": false,
            "min": null,
            "expect": null,
            "max": null,
            "unit": null,
            "sfc_name": "read_pid"
        }
        ,{
            "group": "Reboot",
            "hidden": false,
            "tasktype": 1,
            "item": "",
            "script": "task_runeach",
            "args": ["reboot_and_enter_dl_mode"],
            "auto": false,
            "min": null,
            "expect": null,
            "max": null,
            "unit": null,
            "sfc_name": null
        }
        ,{
            "group": "Enter DL Mode",
            "hidden": false,
            "tasktype": 1,
            "item": "",
            "script": "task_runeach",
            "args": ["enter_burn_mode"],
            "auto": false,
            "min": null,
            "expect": null,
            "max": null,
            "unit": null,
            "sfc_name": "enter_dl_mode"
        }
        ,{
            "group": "Press Start",
            "hidden": false,
            "tasktype": 30,
            "item": "",
            "script": null,
            "args": "start",
            "auto": false,
            "min": null,
            "expect": null,
            "max": null,
            "unit": null,
            "sfc_name": "press_start"
        }
        ,{
            "group": "Downloading",
            "hidden": false,
            "tasktype": 1,
            "item": "",
            "script": "task_runeach",
            "args": ["sap109_downlaod"],
            "auto": false,
            "min": null,
            "expect": null,
            "max": null,
            "unit": null,
            "sfc_name": "download"
        }
        ,{
            "group": "Press Stop",
            "hidden": false,
            "tasktype": 30,
            "item": "",
            "script": null,
            "args": "stop",
            "auto": false,
            "min": null,
            "expect": null,
            "max": null,
            "unit": null,
            "sfc_name": "press_stop"
        }
    ]
}

